xugrid/__init__.py
xugrid/constants.py
xugrid/conversion.py
xugrid/meshkernel_utils.py
xugrid/core/accessorbase.py
xugrid/core/common.py
xugrid/core/dataarray_accessor.py
xugrid/core/dataset_accessor.py
xugrid/core/sparse.py
xugrid/core/utils.py
xugrid/core/wrap.py
xugrid/data/__init__.py
xugrid/data/registry.txt
xugrid/data/sample_data.py
xugrid/data/synthetic.py
xugrid/plot/__init__.py
xugrid/plot/plot.py
xugrid/plot/utils.py
xugrid/regrid/gridder.py
xugrid/regrid/nanpercentile.py
xugrid/regrid/network.py
xugrid/regrid/overlap_1d.py
xugrid/regrid/reduce.py
xugrid/regrid/regridder.py
xugrid/regrid/structured.py
xugrid/regrid/unstructured.py
xugrid/regrid/utils.py
xugrid/ugrid/__init__.py
xugrid/ugrid/burn.py
xugrid/ugrid/connectivity.py
xugrid/ugrid/conventions.py
xugrid/ugrid/interpolate.py
xugrid/ugrid/partitioning.py
xugrid/ugrid/polygonize.py
xugrid/ugrid/selection_utils.py
xugrid/ugrid/snapping.py
xugrid/ugrid/ugrid1d.py
xugrid/ugrid/ugrid2d.py
xugrid/ugrid/ugridbase.py
xugrid/ugrid/voronoi.py
xugrid-0.14.3.dist-info/METADATA
xugrid-0.14.3.dist-info/WHEEL
xugrid-0.14.3.dist-info/licenses/LICENSE
xugrid-0.14.3.dist-info/RECORD
