Metadata-Version: 2.4
Name: xugrid
Version: 0.14.3
Summary: Xarray extension for unstructured grids
Project-URL: Home, https://github.com/deltares/xugrid
Project-URL: Code, https://github.com/deltares/xugrid
Project-URL: Issues, https://github.com/deltares/xugrid/issues
Maintainer-email: Huite Bootsma <huite.bootsma@deltares.nl>
License: MIT
License-File: LICENSE
Keywords: mesh,ugrid,unstructured grid,xarray
Classifier: Development Status :: 3 - Alpha
Classifier: Intended Audience :: Science/Research
Classifier: License :: OSI Approved :: MIT License
Classifier: Operating System :: OS Independent
Classifier: Programming Language :: Python
Classifier: Programming Language :: Python :: 3
Classifier: Programming Language :: Python :: 3.10
Classifier: Programming Language :: Python :: 3.11
Classifier: Programming Language :: Python :: 3.12
Classifier: Programming Language :: Python :: 3.13
Classifier: Programming Language :: Python :: Implementation :: CPython
Classifier: Topic :: Scientific/Engineering
Requires-Python: >=3.10
Requires-Dist: dask>=2025.1.0
Requires-Dist: numba
Requires-Dist: numba-celltree>=0.4.1
Requires-Dist: numpy
Requires-Dist: pandas
Requires-Dist: pooch
Requires-Dist: scipy
Requires-Dist: xarray
Provides-Extra: all
Requires-Dist: geopandas; extra == 'all'
Requires-Dist: mapbox-earcut; extra == 'all'
Requires-Dist: matplotlib; extra == 'all'
Requires-Dist: meshkernel>=3.0.0; extra == 'all'
Requires-Dist: netcdf4; extra == 'all'
Requires-Dist: pooch; extra == 'all'
Requires-Dist: pyproj; extra == 'all'
Requires-Dist: shapely>=2.0; extra == 'all'
Requires-Dist: zarr; extra == 'all'
